GitManager/__init__.py
GitManager/__main__.py
GitManager/main.py
GitManager/commands/__init__.py
GitManager/commands/clone.py
GitManager/commands/fetch.py
GitManager/commands/gc.py
GitManager/commands/lister.py
GitManager/commands/pull.py
GitManager/commands/push.py
GitManager/commands/reconfigure.py
GitManager/commands/setup.py
GitManager/commands/state.py
GitManager/commands/status.py
GitManager/config/__init__.py
GitManager/config/file.py
GitManager/config/line.py
GitManager/config/tree.py
GitManager/repo/__init__.py
GitManager/repo/description.py
GitManager/repo/finder.py
GitManager/repo/implementation.py
GitManager/utils/__init__.py
GitManager/utils/format.py
GitManager/utils/run.py
git_manager-0.2.0.data/scripts/git-manager
git_manager-0.2.0.dist-info/DESCRIPTION.rst
git_manager-0.2.0.dist-info/METADATA
git_manager-0.2.0.dist-info/RECORD
git_manager-0.2.0.dist-info/WHEEL
git_manager-0.2.0.dist-info/metadata.json
git_manager-0.2.0.dist-info/top_level.txt
