Metadata-Version: 2.0
Name: git-manager
Version: 0.2.0
Summary: Manages multiple git repositories
Home-page: https://github.com/tkw1536/GitManager
Author: Tom Wiesing
Author-email: tkw01536@gmail.com
License: MIT
Platform: UNKNOWN
Classifier: Programming Language :: Python :: 3
Classifier: License :: OSI Approved :: MIT License
Classifier: Intended Audience :: Developers
Classifier: Topic :: Utilities
